{
  "hash": "edb5d2a4",
  "configHash": "32101e62",
  "lockfileHash": "d6beefd2",
  "browserHash": "0ce8aee9",
  "optimized": {
    "@vue/devtools-api": {
      "src": "../../../../node_modules/@vue/devtools-api/dist/index.js",
      "file": "@vue_devtools-api.js",
      "fileHash": "d283a926",
      "needsInterop": false
    },
    "@vuepress/shared": {
      "src": "../../../../node_modules/@vuepress/shared/dist/index.js",
      "file": "@vuepress_shared.js",
      "fileHash": "a73d9c62",
      "needsInterop": false
    },
    "vue": {
      "src": "../../../../node_modules/vue/dist/vue.runtime.esm-bundler.js",
      "file": "vue.js",
      "fileHash": "11399db8",
      "needsInterop": false
    },
    "vue-router": {
      "src": "../../../../node_modules/vue-router/dist/vue-router.esm-bundler.js",
      "file": "vue-router.js",
      "fileHash": "fd76988e",
      "needsInterop": false
    }
  },
  "chunks": {
    "chunk-HVR2FF6M": {
      "file": "chunk-HVR2FF6M.js"
    }
  }
}